{
    "name": "congen",
    "namespace": "nslib::congen::shiftgen",
    "reps": [
        {
            "name": "NeuronPopRep",
            "includes" : [ "<nslib/Color.h>" ],
            "namespace": "nslib::congen::shiftgen",
            "properties": [
                {
                    "name": "color",
                    "type": "Color"
                }
            ],
            "types": [ ]
        },
        {
            "name": "ConnectionArrowRep",
            "namespace": "nslib::congen::shiftgen",
            "properties": [
                {
                    "name": "width",
                    "type": "uint"
                }
            ],
            "types": [ ]
        }

    ]
}
